setup.py
pacer/__init__.py
pacer/computation_engine.py
pacer/dill_multiproc.py
pacer/fs_cache.py
pacer/remote_debug.py
pacer/std_logger.py
pacer.egg-info/PKG-INFO
pacer.egg-info/SOURCES.txt
pacer.egg-info/dependency_links.txt
pacer.egg-info/not-zip-safe
pacer.egg-info/requires.txt
pacer.egg-info/top_level.txt