Metadata-Version: 1.0
Name: pacer
Version: 0.30.6
Summary: pacer is a lightweight Python package for implementing distributed data processing workflows.
Home-page: https://ssdmsource.ethz.ch/sis/pacer/tree/master
Author: Uwe Schmitt
Author-email: uwe.schmitt@id.ethz.ch
License: http://opensource.org/licenses/GPL-3.0
Platform: UNKNOWN
